invQ/__init__.py
invQ/calc_invQ.py
invQ-0.1.1.dist-info/LICENSE
invQ-0.1.1.dist-info/METADATA
invQ-0.1.1.dist-info/WHEEL
invQ-0.1.1.dist-info/entry_points.txt
invQ-0.1.1.dist-info/top_level.txt
invQ-0.1.1.dist-info/RECORD
