Metadata-Version: 2.1
Name: invQ
Version: 0.1.1
Summary: A Python package to calculate the angles of quaternions with respect to a reference quaternion considering the point group symmetry of the rigid body
Home-page: https://github.com/sumitavakundu007/invQ
Author: Sumitava Kundu
Author-email: kundusumitava@gmail.com
License: UNKNOWN
Project-URL: Bug Reports, https://github.com/sumitavakundu007/invQ/issues
Project-URL: Say Thanks!, http://saythanks.io/to/example
Project-URL: Source, https://github.com/sumitavakundu007/invQ/
Keywords: sample,setuptools,development
Platform: UNKNOWN
Classifier: Intended Audience :: Developers
Classifier: Topic :: Software Development :: Build Tools
Classifier: License :: OSI Approved :: MIT License
Classifier: Programming Language :: Python :: 3
Classifier: Programming Language :: Python :: 3.6
Classifier: Programming Language :: Python :: 3.7
Classifier: Programming Language :: Python :: 3.8
Classifier: Programming Language :: Python :: 3.9
Requires-Python: >=3.6
License-File: LICENSE
Requires-Dist: rowan
